LICENSE
MANIFEST.in
Makefile
NEWS
README
TODO
setup.cfg
setup.py
tox.ini
dev/test
storm/__init__.py
storm/base.py
storm/cache.py
storm/cextensions.c
storm/database.py
storm/event.py
storm/exceptions.py
storm/expr.py
storm/info.py
storm/locals.py
storm/properties.py
storm/references.py
storm/sqlobject.py
storm/store.py
storm/testing.py
storm/tracer.py
storm/tz.py
storm/uri.py
storm/variables.py
storm/wsgi.py
storm/xid.py
storm.egg-info/PKG-INFO
storm.egg-info/SOURCES.txt
storm.egg-info/dependency_links.txt
storm.egg-info/not-zip-safe
storm.egg-info/requires.txt
storm.egg-info/top_level.txt
storm/databases/__init__.py
storm/databases/mysql.py
storm/databases/postgres.py
storm/databases/sqlite.py
storm/docs/Makefile
storm/docs/__init__.py
storm/docs/api.rst
storm/docs/conf.py
storm/docs/index.rst
storm/docs/infoheritance.rst
storm/docs/tutorial.rst
storm/docs/zope.rst
storm/schema/__init__.py
storm/schema/patch.py
storm/schema/schema.py
storm/schema/sharding.py
storm/tests/__init__.py
storm/tests/base.py
storm/tests/cache.py
storm/tests/database.py
storm/tests/event.py
storm/tests/expr.py
storm/tests/helper.py
storm/tests/info.py
storm/tests/mocker.py
storm/tests/properties.py
storm/tests/sqlobject.py
storm/tests/tracer.py
storm/tests/uri.py
storm/tests/variables.py
storm/tests/wsgi.py
storm/tests/databases/__init__.py
storm/tests/databases/base.py
storm/tests/databases/mysql.py
storm/tests/databases/postgres.py
storm/tests/databases/proxy.py
storm/tests/databases/sqlite.py
storm/tests/django/__init__.py
storm/tests/schema/__init__.py
storm/tests/schema/patch.py
storm/tests/schema/schema.py
storm/tests/schema/sharding.py
storm/tests/store/__init__.py
storm/tests/store/base.py
storm/tests/store/block.py
storm/tests/store/mysql.py
storm/tests/store/postgres.py
storm/tests/store/sqlite.py
storm/tests/twisted/__init__.py
storm/tests/twisted/transact.py
storm/tests/zope/__init__.py
storm/tests/zope/adapters.py
storm/tests/zope/testing.py
storm/tests/zope/zstorm.py
storm/twisted/__init__.py
storm/twisted/testing.py
storm/twisted/transact.py
storm/zope/__init__.py
storm/zope/adapters.py
storm/zope/configure.zcml
storm/zope/interfaces.py
