Metadata-Version: 2.4
Name: storm
Version: 1.1
Summary: Storm is an object-relational mapper (ORM) for Python developed at Canonical.
Home-page: https://storm.canonical.com
Download-URL: https://launchpad.net/storm/+download
Author: Gustavo Niemeyer
Author-email: gustavo@niemeyer.net
Maintainer: Storm Developers
Maintainer-email: storm@lists.canonical.com
License: LGPL
Classifier: Development Status :: 5 - Production/Stable
Classifier: Intended Audience :: Developers
Classifier: License :: OSI Approved :: GNU Library or Lesser General Public License (LGPL)
Classifier: Programming Language :: Python
Classifier: Programming Language :: Python :: 3
Classifier: Programming Language :: Python :: 3.6
Classifier: Programming Language :: Python :: 3.7
Classifier: Programming Language :: Python :: 3.8
Classifier: Programming Language :: Python :: 3.9
Classifier: Programming Language :: Python :: 3.10
Classifier: Programming Language :: Python :: 3.11
Classifier: Programming Language :: Python :: 3.12
Classifier: Programming Language :: Python :: 3.13
Classifier: Programming Language :: Python :: 3.14
Classifier: Topic :: Database
Classifier: Topic :: Database :: Front-Ends
Classifier: Topic :: Software Development :: Libraries :: Python Modules
Requires-Python: >=3.6
License-File: LICENSE
Requires-Dist: packaging>=14.1
Provides-Extra: doc
Requires-Dist: fixtures; extra == "doc"
Requires-Dist: sphinx; extra == "doc"
Requires-Dist: sphinx-epytext; extra == "doc"
Provides-Extra: test
Requires-Dist: fixtures>=1.3.0; extra == "test"
Requires-Dist: mysqlclient; extra == "test"
Requires-Dist: pgbouncer>=0.0.7; extra == "test"
Requires-Dist: postgresfixture; extra == "test"
Requires-Dist: psycopg2>=2.3.0; extra == "test"
Requires-Dist: testresources>=0.2.4; extra == "test"
Requires-Dist: testtools>=0.9.8; extra == "test"
Requires-Dist: timeline>=0.0.2; extra == "test"
Requires-Dist: transaction>=1.0.0; extra == "test"
Requires-Dist: Twisted>=10.0.0; extra == "test"
Requires-Dist: zope.component>=3.8.0; extra == "test"
Requires-Dist: zope.configuration; extra == "test"
Requires-Dist: zope.interface>=4.0.0; extra == "test"
Requires-Dist: zope.security>=3.7.2; extra == "test"
Dynamic: author
Dynamic: author-email
Dynamic: classifier
Dynamic: description
Dynamic: description-content-type
Dynamic: download-url
Dynamic: home-page
Dynamic: license
Dynamic: license-file
Dynamic: maintainer
Dynamic: maintainer-email
Dynamic: provides-extra
Dynamic: requires-dist
Dynamic: requires-python
Dynamic: summary
